khaeru/__init__.py
khaeru-1.0.0.dist-info/LICENSE
khaeru-1.0.0.dist-info/METADATA
khaeru-1.0.0.dist-info/WHEEL
khaeru-1.0.0.dist-info/top_level.txt
khaeru-1.0.0.dist-info/RECORD
