Metadata-Version: 2.1
Name: khaeru
Version: 1.0.0
Summary: Python miscellany
Home-page: https://github.com/khaeru/py
Author: Paul Natsuo Kishimoto
Author-email: mail@paul.kishimoto.name
License: GPLv3
Platform: UNKNOWN
Requires-Dist: setuptools (>=41)
